check_dkim/__init__.py
check_dkim-0.1.0.dist-info/entry_points.txt
check_dkim-0.1.0.dist-info/LICENSE
check_dkim-0.1.0.dist-info/WHEEL
check_dkim-0.1.0.dist-info/METADATA
check_dkim-0.1.0.dist-info/RECORD
